{
"type": "FeatureCollection",
"name": "geo_25_指定療養通所介護",
"crs": { "type": "name", "properties": { "name": "urn:ogc:def:crs:OGC:1.3:CRS84" } },
"features": [
{ "type": "Feature", "properties": { "内容": "療養通所　always【指定療養通所介護】滋賀県大津市追分町１６番２１号", "url": "https://www.kaigokensaku.mhlw.go.jp/25/index.php?action_kouhyou_detail_004_kani=true&JigyosyoCd=2590100836-00&ServiceCd=&Type=search", "url2": "bridge-nurse.com" }, "geometry": { "type": "Point", "coordinates": [ 135.835341793254088, 34.993545365588609 ] } },
{ "type": "Feature", "properties": { "内容": "有限会社ケアサポートリブ【指定療養通所介護】滋賀県大津市仰木の里東一丁目15-20", "url": "https://www.kaigokensaku.mhlw.go.jp/25/index.php?action_kouhyou_detail_004_kani=true&JigyosyoCd=2570101192-00&ServiceCd=&Type=search", "url2": "http：//carelive" }, "geometry": { "type": "Point", "coordinates": [ 135.8933676, 35.1011895 ] } },
{ "type": "Feature", "properties": { "内容": "療養通所介護　まほろば【指定療養通所介護】滋賀県長浜市下坂中町200番地1", "url": "https://www.kaigokensaku.mhlw.go.jp/25/index.php?action_kouhyou_detail_004_kani=true&JigyosyoCd=2590300246-00&ServiceCd=&Type=search", "url2": "http：//o-kourakukai.or.jp" }, "geometry": { "type": "Point", "coordinates": [ 136.2840519, 35.3650723 ] } },
{ "type": "Feature", "properties": { "内容": "デイケアセンターなかさと【指定療養通所介護】滋賀県野洲市八夫2077", "url": "https://www.kaigokensaku.mhlw.go.jp/25/index.php?action_kouhyou_detail_004_kani=true&JigyosyoCd=2571300363-00&ServiceCd=&Type=search", "url2": "http://www.konan-psy.or.jp" }, "geometry": { "type": "Point", "coordinates": [ 136.021453699999938, 35.0887735 ] } },
{ "type": "Feature", "properties": { "内容": "公益社団法人滋賀県看護協会療養通所介護事業所【指定療養通所介護】滋賀県東近江市八日市上之町1番39号公益社団法人滋賀県看護協会在宅ケアセンターみのり", "url": "https://www.kaigokensaku.mhlw.go.jp/25/index.php?action_kouhyou_detail_004_kani=true&JigyosyoCd=2560590016-00&ServiceCd=&Type=search", "url2": null }, "geometry": { "type": "Point", "coordinates": [ 136.2044835, 35.1140082 ] } }
]
}
